test/__init__.py
test/test_account_api.py
test/test_areas_dto.py
test/test_at_a_glance_view_model.py
test/test_attachment_api.py
test/test_attachment_view_model.py
test/test_avalanche_activity_obs2_dto.py
test/test_avalanche_activity_obs2_view_model.py
test/test_avalanche_activity_obs_dto.py
test/test_avalanche_activity_obs_view_model.py
test/test_avalanche_danger_obs_dto.py
test/test_avalanche_danger_obs_view_model.py
test/test_avalanche_eval_problem2_dto.py
test/test_avalanche_eval_problem2_view_model.py
test/test_avalanche_eval_problem_view_model.py
test/test_avalanche_evaluation2_view_model.py
test/test_avalanche_evaluation3_dto.py
test/test_avalanche_evaluation3_view_model.py
test/test_avalanche_evaluation_view_model.py
test/test_avalanche_obs_dto.py
test/test_avalanche_obs_view_model.py
test/test_compression_test_dto.py
test/test_compression_test_view_model.py
test/test_county_dto.py
test/test_create_account_request.py
test/test_create_registration_request_dto.py
test/test_create_registration_response_dto.py
test/test_create_trip_dto.py
test/test_damage_obs_dto.py
test/test_damage_obs_view_model.py
test/test_danger_obs_dto.py
test/test_danger_obs_view_model.py
test/test_density_profile_dto.py
test/test_density_profile_layer_dto.py
test/test_finish_trip_dto.py
test/test_forecast_region_dto.py
test/test_forecast_region_sub_region_dto.py
test/test_general_obs_api.py
test/test_general_observation_edit_model.py
test/test_general_observation_view_model.py
test/test_geo_code_api.py
test/test_geo_location_info.py
test/test_get_token_request_dto.py
test/test_get_token_response_dto.py
test/test_helptext_api.py
test/test_helptext_dto.py
test/test_ice_cover_obs_dto.py
test/test_ice_cover_view_model.py
test/test_ice_thickness_dto.py
test/test_ice_thickness_layer_dto.py
test/test_ice_thickness_layer_view_model.py
test/test_ice_thickness_view_model.py
test/test_incident_dto.py
test/test_incident_urls_dto.py
test/test_incident_view_model.py
test/test_kdv_element.py
varsom_regobs_client-1.0.0.dist-info/METADATA
varsom_regobs_client-1.0.0.dist-info/WHEEL
varsom_regobs_client-1.0.0.dist-info/top_level.txt
varsom_regobs_client-1.0.0.dist-info/RECORD
