Metadata-Version: 2.1
Name: varsom-regobs-client
Version: 1.0.0
Summary: RegObs API
Home-page: https://github.com/NVE/python-varsom-regobs-client
Author: UNKNOWN
Author-email: regobs@nve.no
License: UNKNOWN
Keywords: Swagger,RegObs API
Platform: UNKNOWN
Requires-Dist: urllib3 (>=1.15)
Requires-Dist: six (>=1.10)
Requires-Dist: certifi
Requires-Dist: python-dateutil
